{"context":{"@id":"http://schema.org/Report","@type":"rdfs:Class","rdfs:comment":"A Report generated by governmental or non-governmental organization.","rdfs:label":"Report","rdfs:subClassOf":{"@id":"http://schema.org/Article"}},"properties":[{"@id":"http://schema.org/reportNumber","@type":"rdf:Property","http://schema.org/domainIncludes":{"@id":"http://schema.org/Report"},"http://schema.org/rangeIncludes":{"@id":"http://schema.org/Text"},"rdfs:comment":"The number or other unique designator assigned to a Report by the publishing organization.","rdfs:label":"reportNumber"}]}