{"context":{"@id":"http://schema.org/WinAction","@type":"rdfs:Class","rdfs:comment":"The act of achieving victory in a competitive activity.","rdfs:label":"WinAction","rdfs:subClassOf":{"@id":"http://schema.org/AchieveAction"}},"properties":[{"@id":"http://schema.org/loser","@type":"rdf:Property","http://schema.org/domainIncludes":{"@id":"http://schema.org/WinAction"},"http://schema.org/rangeIncludes":{"@id":"http://schema.org/Person"},"rdfs:comment":"A sub property of participant. The loser of the action.","rdfs:label":"loser","rdfs:subPropertyOf":{"@id":"http://schema.org/participant"}}]}